EasyFiles.py
__init__.py
EasyFiles-0.0.1.dist-info/LICENSE
EasyFiles-0.0.1.dist-info/METADATA
EasyFiles-0.0.1.dist-info/WHEEL
EasyFiles-0.0.1.dist-info/top_level.txt
EasyFiles-0.0.1.dist-info/RECORD
